oneNeuronPerceptron/Pereceptron.py
oneNeuronPerceptron/__init__.py
oneNeuronPerceptron/all_utils.py
oneNeuron_pypi_Rishbah_76-0.0.2.dist-info/LICENSE
oneNeuron_pypi_Rishbah_76-0.0.2.dist-info/METADATA
oneNeuron_pypi_Rishbah_76-0.0.2.dist-info/WHEEL
oneNeuron_pypi_Rishbah_76-0.0.2.dist-info/top_level.txt
oneNeuron_pypi_Rishbah_76-0.0.2.dist-info/RECORD
