Metadata-Version: 2.1
Name: oneNeuron-pypi-Rishbah-76
Version: 0.0.2
Summary: It is a Pereceptron Implementation
Home-page: https://github.com/Rishbah-76/oneNeuron_pypi
Author: Rishbah-76
Author-email: rbrishabh76@example.com
License: UNKNOWN
Project-URL: Bug Tracker, https://github.com/Rishbah-76/oneNeuron_pypi/issues
Platform: UNKNOWN
Classifier: Programming Language :: Python :: 3
Classifier: License :: OSI Approved :: MIT License
Classifier: Operating System :: OS Independent
Requires-Python: >=3.7
License-File: LICENSE
Requires-Dist: numpy
Requires-Dist: tqdm
Requires-Dist: matplotlib
Requires-Dist: pandas
Requires-Dist: joblib
